codat/__init__.py
codat/configuration.py
codat/connections.py
codat/expenses.py
codat/mapping_options.py
codat/sdk.py
codat/sync.py
codat/sync_status.py
codat/transaction_status.py
codat/models/__init__.py
codat/models/operations/__init__.py
codat/models/operations/create_expense_dataset.py
codat/models/operations/create_partner_expense_connection.py
codat/models/operations/get_company_configuration.py
codat/models/operations/get_last_successful_sync.py
codat/models/operations/get_latest_sync.py
codat/models/operations/get_mapping_options.py
codat/models/operations/get_sync_by_id.py
codat/models/operations/get_sync_transaction.py
codat/models/operations/intiate_sync.py
codat/models/operations/list_sync_transactions.py
codat/models/operations/list_syncs.py
codat/models/operations/save_company_configuration.py
codat/models/operations/upload_attachment.py
codat/models/shared/__init__.py
codat/models/shared/accountmappinginfo.py
codat/models/shared/attachment.py
codat/models/shared/bankaccount.py
codat/models/shared/codaterrormessage.py
codat/models/shared/companyconfiguration.py
codat/models/shared/companysyncstatus.py
codat/models/shared/createexpenserequest.py
codat/models/shared/createexpenseresponse.py
codat/models/shared/customer.py
codat/models/shared/dataconnection.py
codat/models/shared/dataconnectionerror.py
codat/models/shared/dataconnectionstatus_enum.py
codat/models/shared/expensetransaction.py
codat/models/shared/expensetransactionline.py
codat/models/shared/hallink.py
codat/models/shared/integrationtype_enum.py
codat/models/shared/mappingoptions.py
codat/models/shared/postsync.py
codat/models/shared/recordref.py
codat/models/shared/security.py
codat/models/shared/supplier.py
codat/models/shared/syncinitiated.py
codat/models/shared/taxratemappinginfo.py
codat/models/shared/trackingcategorymappinginfo.py
codat/models/shared/transactionmetadata.py
codat/models/shared/transactionmetadatalist.py
codat/models/shared/transactionstatus_enum.py
codat_expenses-0.8.6.dist-info/METADATA
codat_expenses-0.8.6.dist-info/WHEEL
codat_expenses-0.8.6.dist-info/top_level.txt
codat_expenses-0.8.6.dist-info/RECORD
